bobrFlow/__init__.py
bobrFlow/db_connectors.py
bobrFlow/google_docs.py
bobrFlow/helpers.py
bobrFlow/telegram_client.py
BobrFlow-0.1.7.dist-info/METADATA
BobrFlow-0.1.7.dist-info/WHEEL
BobrFlow-0.1.7.dist-info/top_level.txt
BobrFlow-0.1.7.dist-info/RECORD
