Metadata-Version: 2.1
Name: BobrFlow
Version: 0.1.7
Summary: Tools designed to simplify routine tasks for analysts, enabling faster and more efficient data processing and analysis
Author: Artsem Bobr
Author-email: artyombobr@gmail.com
License: MIT
Classifier: Programming Language :: Python :: 3
Classifier: License :: OSI Approved :: MIT License
Classifier: Operating System :: OS Independent
Requires-Python: >=3.9
Requires-Dist: gspread>=6.1.4
Requires-Dist: oauth2client>=4.1.3
Requires-Dist: pandas>=2.2.3
Requires-Dist: setuptools>=68.2.2
Requires-Dist: snowflake_connector_python>=3.10.1
Requires-Dist: snowflake_snowpark_python>=1.17.0
Requires-Dist: pysocks>=1.7.1
